AUTHORS
CHANGELOG
INSTALL
LICENSE
MANIFEST.in
README
VERSION
setup.py
sphinxcontrib/__init__.py
sphinxcontrib/testbuild/__init__.py
sphinxcontrib/testbuild/tests.py
sphinxcontrib_testbuild.egg-info/PKG-INFO
sphinxcontrib_testbuild.egg-info/SOURCES.txt
sphinxcontrib_testbuild.egg-info/dependency_links.txt
sphinxcontrib_testbuild.egg-info/namespace_packages.txt
sphinxcontrib_testbuild.egg-info/not-zip-safe
sphinxcontrib_testbuild.egg-info/requires.txt
sphinxcontrib_testbuild.egg-info/top_level.txt