Metadata-Version: 1.1
Name: sphinxcontrib-testbuild
Version: 0.1.3
Summary: Test Sphinx builds with Python tests.
Home-page: https://github.com/benoitbryon/sphinxcontrib-testbuild
Author: Benoît Bryon
Author-email: benoit@marmelune.net
License: BSD
Platform: any
Classifier: Development Status :: 4 - Beta
Classifier: Environment :: Console
Classifier: Environment :: Web Environment
Classifier: Intended Audience :: Developers
Classifier: License :: OSI Approved :: BSD License
Classifier: Operating System :: OS Independent
Classifier: Programming Language :: Python
Classifier: Topic :: Documentation
Classifier: Topic :: Utilities
